jigeum/__init__.py
jigeum/seoul.py
SWjigeum-0.3.0.dist-info/METADATA
SWjigeum-0.3.0.dist-info/WHEEL
SWjigeum-0.3.0.dist-info/entry_points.txt
SWjigeum-0.3.0.dist-info/top_level.txt
SWjigeum-0.3.0.dist-info/RECORD
