Metadata-Version: 2.1
Name: SWjigeum
Version: 0.3.0
Summary: Default template for PDM package
Author-email: GITSangWoo <dogcenta@gmail.com>
License: MIT
Requires-Python: >=3.11
